resreservation
