Metadata-Version: 1.0
Name: ResourceReservation
Version: 1.0.4
Summary: Resource Reservation plugin for Trac
Home-page: http://trac-hacks.org/wiki/ResourceReservationPlugin
Author: Roberto Longobardi
Author-email: seccanj@gmail.com
License: BSD. See the file LICENSE.txt contained in the package.
Download-URL: http://sourceforge.net/projects/resreserv4trac
Keywords: trac plugin project resource management planning schedule
Platform: UNKNOWN
